Metadata-Version: 2.1
Name: arche
Version: 0.3.6
Summary: Analyze Scrapy Cloud data
Home-page: http://github.com/scrapinghub/arche
Maintainer: Scrapinghub, manycoding
Maintainer-email: info@scrapinghub.com
License: MIT
Keywords: scrapinghub,scraping,data,data-visualization,data-analysis,pandas
Platform: UNKNOWN
Classifier: Development Status :: 5 - Production/Stable
Classifier: Intended Audience :: Developers
Classifier: Programming Language :: Python :: 3.7
Provides-Extra: docs
Provides-Extra: pep8tests
Provides-Extra: tests
